lccnorm/__init__.py
lccnorm/__version__.py
lccnorm/lccnorm.py
lccnorm-1.0.0.dist-info/LICENSE
lccnorm-1.0.0.dist-info/METADATA
lccnorm-1.0.0.dist-info/WHEEL
lccnorm-1.0.0.dist-info/top_level.txt
lccnorm-1.0.0.dist-info/RECORD
