Metadata-Version: 2.1
Name: lccnorm
Version: 1.0.0
Summary: Normalize Library of Congress Control Numbers.
Home-page: https://github.com/seanredmond/lccnorm-py
Author: Sean Redmond
Author-email: github-smr@sneakemail.com
License: MIT
Platform: UNKNOWN
Classifier: License :: OSI Approved :: MIT License
Classifier: Programming Language :: Python
Classifier: Programming Language :: Python :: 3
Classifier: Programming Language :: Python :: 3.6
Requires-Python: >=2.6.0
